AmorphSim
