Metadata-Version: 1.0
Name: AmorphSim
Version: 0.2
Summary: Tool for simulating amorphous Materials
Home-page: https://github.com/CSSFrancis/AmorphSim
Author: CSSFrancis
Author-email: csfrancis@wisc.edu
License: UNKNOWN
Keywords: Simulations STEM Electron Microscopy Glass
Platform: UNKNOWN
